tpds_extension/ecc608_sip_support/extension.yaml
tpds_extension/ecc608_sip_support/setup.py
tpds_extension/ecc608_sip_support/version.py
tpds_extension/ecc608_sip_support/TrustFlex/asymmetric_authentication/PIC32CMLS60-Asymmetric Authentication.ipynb
tpds_extension/ecc608_sip_support/TrustFlex/asymmetric_authentication/cust_def_device.c
tpds_extension/ecc608_sip_support/TrustFlex/asymmetric_authentication/cust_def_device.h
tpds_extension/ecc608_sip_support/TrustFlex/asymmetric_authentication/cust_def_signer.c
tpds_extension/ecc608_sip_support/TrustFlex/asymmetric_authentication/cust_def_signer.h
tpds_extension/ecc608_sip_support/TrustFlex/asymmetric_authentication/firmware.zip
tpds_extension/ecc608_sip_support/TrustFlex/asymmetric_authentication/assets/PIC32CMLS60-Asymmetric Authentication.md
tpds_extension/ecc608_sip_support/TrustFlex/asymmetric_authentication/assets/images/asymmetric auth.png
tpds_extension/ecc608_sip_support/TrustFlex/asymmetric_authentication/assets/images/c-snippet.PNG
tpds_extension/ecc608_sip_support/TrustFlex/asymmetric_authentication/assets/images/crypto-assets.png
tpds_extension/ecc608_sip_support/TrustFlex/asymmetric_authentication/assets/images/td-Accessory-Asymmetric-Auth.png
tpds_extension/ecc608_sip_support/TrustFlex/asymmetric_authentication/assets/images/usecase_steps.png
tpds_extension/ecc608_sip_support/TrustFlex/asymmetric_authentication/assets/python/asymmetric_authentication.py
tpds_extension/ecc608_sip_support/TrustFlex/cloud_connect/PIC32CMLS60-AWSCustomPKI-TFLEX.ipynb
tpds_extension/ecc608_sip_support/TrustFlex/cloud_connect/PIC32CMLS60-AWSIoTAuth-TFLEX.ipynb
tpds_extension/ecc608_sip_support/TrustFlex/cloud_connect/PIC32CMLS60-AzureCustomPKI-TFLEX.ipynb
tpds_extension/ecc608_sip_support/TrustFlex/cloud_connect/PIC32CMLS60-AzureIoTAuth-TFLEX.ipynb
tpds_extension/ecc608_sip_support/TrustFlex/cloud_connect/aws_connect.h
tpds_extension/ecc608_sip_support/TrustFlex/cloud_connect/azure_connect.h
tpds_extension_ecc608_sip_support-1.6.5.dist-info/METADATA
tpds_extension_ecc608_sip_support-1.6.5.dist-info/WHEEL
tpds_extension_ecc608_sip_support-1.6.5.dist-info/top_level.txt
tpds_extension_ecc608_sip_support-1.6.5.dist-info/RECORD
