Metadata-Version: 2.1
Name: tpds-extension-ecc608-sip-support
Version: 1.6.5
Summary: Microchip(SPG) Trust Platform - ECC608 SIP Device Support
Home-page: https://www.microchip.com/TrustPlatform
Author: Microchip Technology
Author-email: SPG.Tools@microchip.com
Classifier: License :: Other/Proprietary License
Classifier: Development Status :: 4 - Beta
Classifier: Programming Language :: Python :: 3
Classifier: Operating System :: OS Independent
Requires-Python: >=3.6
